{
	"agcgw_all":{
		"CN":"connect-drcn.dbankcloud.cn",
		"CN_back":"connect-drcn.hispace.hicloud.com",
		"DE":"connect-dre.dbankcloud.cn",
		"DE_back":"connect-dre.hispace.hicloud.com",
		"RU":"connect-drru.dbankcloud.cn",
		"RU_back":"connect-drru.hispace.hicloud.com",
		"SG":"connect-dra.dbankcloud.cn",
		"SG_back":"connect-dra.hispace.hicloud.com"
	},
	"client":{
		"cp_id":"2640964000023443630",
		"product_id":"737518067794323985",
		"client_id":"807954014481171456",
		"client_secret":"B32BA9C3393DA989AD911D2F5FD54754A3BDE38CCA25EEA0FD086D568A438382",
		"project_id":"737518067794323985",
		"app_id":"105386491",
		"api_key":"DAEDAIzjKq9uCz/lJPKxcH7lhC+DvgPzMiusuYkv7xlSG6u26XvyomgR3VtzUjSDUAkQiD+kVsQM7MkMjPJSR8nR9ghzJOni48Rekw==",
		"package_name":"thepaws.app"
	},
	"oauth_client":{
		"client_id":"105386491",
		"client_type":1
	},
	"app_info":{
		"app_id":"105386491",
		"package_name":"thepaws.app"
	},
	"configuration_version":"3.0",
	"appInfos":[
		{
			"package_name":"thepaws.app",
			"client":{
				"app_id":"105386491"
			},
			"app_info":{
				"package_name":"thepaws.app",
				"app_id":"105386491"
			},
			"oauth_client":{
				"client_type":1,
				"client_id":"105386491"
			}
		}
	]
}